[{"name":"Erinn","comment":"Hello","date":"2013-09-29","timestamp":1506698223097},{"name":"asdf","comment":"sadf","date":"2017-10-17","timestamp":1508282824},{"name":"asdf","comment":"sadf","date":"2017-10-17","timestamp":1508282910},{"name":"asdf","comment":"sadf","date":"2017-10-17","timestamp":1508283383},{"name":"asdf","comment":"asdfsdafdsafsdfdsafdsa","date":"2017-10-17","timestamp":1508283392},{"name":"asdfsadfdsaf","comment":"&lt;b&gt;hello&lt;\/b&gt;","date":"2017-10-17","timestamp":1508283424},{"name":"sdfasdfsdaf","comment":"sadfdsfdsafdsafdsafdsafdsaf","date":"2017-10-17","timestamp":1508283447}]